judges/__init__.py
judges/base.py
judges/voting_methods.py
judges/classifiers/__init__.py
judges/classifiers/correctness.py
judges/classifiers/hallucination.py
judges/classifiers/harmfulness.py
judges/classifiers/query_quality.py
judges/classifiers/refusal.py
judges/classifiers/auto/__init__.py
judges/classifiers/auto/_metrics.py
judges/classifiers/auto/_prompts.py
judges/classifiers/auto/core.py
judges/cli/__init__.py
judges/cli/entrypoint.py
judges/graders/__init__.py
judges/graders/correctness.py
judges/graders/empathy.py
judges/graders/information_coverage.py
judges/graders/moderator.py
judges/graders/query_quality.py
judges/graders/refusal_detection.py
judges/graders/relevance.py
judges/graders/response_quality.py
judges/graders/story_quality.py
judges/graders/summary_quality.py
judges-0.1.1.dist-info/licenses/LICENSE
judges-0.1.1.dist-info/METADATA
judges-0.1.1.dist-info/WHEEL
judges-0.1.1.dist-info/entry_points.txt
judges-0.1.1.dist-info/top_level.txt
judges-0.1.1.dist-info/RECORD
