Metadata-Version: 2.4
Name: judges
Version: 0.1.1
Summary: A small library of research-backed LLM judges
Author-email: Freddie Vargus <freddie@quotientai.co>
License: Apache 2.0
Keywords: ai,large language models,llm-judge,evaluation,evals
Classifier: Programming Language :: Python :: 3
Classifier: License :: OSI Approved :: Apache Software License
Requires-Python: >=3.10
License-File: LICENSE
Requires-Dist: instructor>=1.8.2
Requires-Dist: pydantic>=2.10.3
Provides-Extra: dev
Requires-Dist: openai-responses>=0.11.2; extra == "dev"
Dynamic: license-file
